setup.py
opinio/__init__.py
opinio/client.py
opinio/constants.py
opinio/errors.py
opinio.egg-info/PKG-INFO
opinio.egg-info/SOURCES.txt
opinio.egg-info/dependency_links.txt
opinio.egg-info/not-zip-safe
opinio.egg-info/pbr.json
opinio.egg-info/requires.txt
opinio.egg-info/top_level.txt