Metadata-Version: 1.1
Name: opinio
Version: 0.0.1
Summary: Python client for Opinio APIs
Home-page: http://sandeepk.in
Author: Sandeep Kumar
Author-email: 4sandeep.kumar@gmail.com
License: UNKNOWN
Platform: UNKNOWN
Classifier: Environment :: Web Environment
Classifier: Intended Audience :: Developers
Classifier: License :: OSI Approved :: BSD License
Classifier: Operating System :: OS Independent
Classifier: Programming Language :: Python
Classifier: Programming Language :: Python :: 3
Classifier: Topic :: Internet :: WWW/HTTP
